[{"date_time":"2008-01-01T00:00:00","first_name":"John","last_name":"Doe","type":"RED_SIGNAL","fine_amount":13.083877166029744},{"date_time":"2008-01-02T00:00:00","first_name":"John","last_name":"Doe","type":"RED_SIGNAL","fine_amount":99.90865586515385},{"date_time":"2008-01-03T00:00:00","first_name":"John","last_name":"Doe","type":"NO_INSURANCE","fine_amount":61.1026317539885},{"date_time":"2008-01-04T00:00:00","first_name":"John","last_name":"Doe","type":"RED_SIGNAL","fine_amount":42.35743986399173},{"date_time":"2008-01-05T00:00:00","first_name":"John","last_name":"Doe","type":"NO_SEATBELT","fine_amount":82.23749790174557},{"date_time":"2008-01-06T00:00:00","first_name":"John","last_name":"Doe","type":"RED_SIGNAL","fine_amount":75.69860581235618},{"date_time":"2008-01-07T00:00:00","first_name":"John","last_name":"Doe","type":"DRUNK_DRIVING","fine_amount":6.489636678694712},{"date_time":"2008-01-08T00:00:00","first_name":"John","last_name":"Doe","type":"DRUNK_DRIVING","fine_amount":59.66250026029728},{"date_time":"2008-01-09T00:00:00","first_name":"John","last_name":"Doe","type":"RED_SIGNAL","fine_amount":47.253184526228495},{"date_time":"2008-01-10T00:00:00","first_name":"John","last_name":"Doe","type":"NO_SEATBELT","fine_amount":40.98062231486099},{"date_time":"2008-01-11T00:00:00","first_name":"John","last_name":"Doe","type":"RED_SIGNAL","fine_amount":37.836308902571176},{"date_time":"2008-01-12T00:00:00","first_name":"John","last_name":"Doe","type":"DRUNK_DRIVING","fine_amount":26.160843670157462},{"date_time":"2008-01-13T00:00:00","first_name":"John","last_name":"Doe","type":"SPEEDING","fine_amount":79.70998398109234},{"date_time":"2008-01-14T00:00:00","first_name":"John","last_name":"Doe","type":"RED_SIGNAL","fine_amount":1.0728364516783921},{"date_time":"2008-01-15T00:00:00","first_name":"John","last_name":"Doe","type":"DRUNK_DRIVING","fine_amount":54.82269006324263},{"date_time":"2008-01-16T00:00:00","first_name":"John","last_name":"Doe","type":"NO_SEATBELT","fine_amount":41.36621999355673},{"date_time":"2008-01-17T00:00:00","first_name":"John","last_name":"Doe","type":"NO_INSURANCE","fine_amount":52.32108885162271},{"date_time":"2008-01-18T00:00:00","first_name":"John","last_name":"Doe","type":"SPEEDING","fine_amount":18.24744631870179},{"date_time":"2008-01-19T00:00:00","first_name":"John","last_name":"Doe","type":"NO_SEATBELT","fine_amount":1.1439381938700133},{"date_time":"2008-01-20T00:00:00","first_name":"John","last_name":"Doe","type":"NO_SEATBELT","fine_amount":6.5593807749328485},{"date_time":"2008-01-21T00:00:00","first_name":"John","last_name":"Doe","type":"DRUNK_DRIVING","fine_amount":46.54854529969981},{"date_time":"2008-01-22T00:00:00","first_name":"John","last_name":"Doe","type":"NO_SEATBELT","fine_amount":89.52063927336776},{"date_time":"2008-01-23T00:00:00","first_name":"John","last_name":"Doe","type":"NO_SEATBELT","fine_amount":51.696116159366035},{"date_time":"2008-01-24T00:00:00","first_name":"John","last_name":"Doe","type":"NO_INSURANCE","fine_amount":28.518173122321382},{"date_time":"2008-01-25T00:00:00","first_name":"John","last_name":"Doe","type":"NO_INSURANCE","fine_amount":33.39753005415222},{"date_time":"2008-01-26T00:00:00","first_name":"John","last_name":"Doe","type":"RED_SIGNAL","fine_amount":89.93098826886165},{"date_time":"2008-01-27T00:00:00","first_name":"John","last_name":"Doe","type":"DRUNK_DRIVING","fine_amount":96.60847351791149},{"date_time":"2008-01-28T00:00:00","first_name":"John","last_name":"Doe","type":"NO_SEATBELT","fine_amount":98.06701122953174},{"date_time":"2008-01-29T00:00:00","first_name":"John","last_name":"Doe","type":"NO_SEATBELT","fine_amount":21.78916465793668},{"date_time":"2008-01-30T00:00:00","first_name":"John","last_name":"Doe","type":"NO_SEATBELT","fine_amount":95.68758012952718},{"date_time":"2008-01-31T00:00:00","first_name":"John","last_name":"Doe","type":"NO_INSURANCE","fine_amount":95.00701711350189},{"date_time":"2008-02-01T00:00:00","first_name":"John","last_name":"Doe","type":"SPEEDING","fine_amount":12.590061691472613},{"date_time":"2008-02-02T00:00:00","first_name":"John","last_name":"Doe","type":"SPEEDING","fine_amount":39.28105556213818},{"date_time":"2008-02-03T00:00:00","first_name":"John","last_name":"Doe","type":"NO_SEATBELT","fine_amount":7.931289443907472},{"date_time":"2008-02-04T00:00:00","first_name":"John","last_name":"Doe","type":"NO_SEATBELT","fine_amount":39.93626563674994},{"date_time":"2008-02-05T00:00:00","first_name":"John","last_name":"Doe","type":"SPEEDING","fine_amount":60.061722358120235},{"date_time":"2008-02-06T00:00:00","first_name":"John","last_name":"Doe","type":"NO_SEATBELT","fine_amount":56.36850279009167},{"date_time":"2008-02-07T00:00:00","first_name":"John","last_name":"Doe","type":"RED_SIGNAL","fine_amount":91.05884161679909},{"date_time":"2008-02-08T00:00:00","first_name":"John","last_name":"Doe","type":"DRUNK_DRIVING","fine_amount":51.001765009858126},{"date_time":"2008-02-09T00:00:00","first_name":"John","last_name":"Doe","type":"RED_SIGNAL","fine_amount":33.900901873828424},{"date_time":"2008-02-10T00:00:00","first_name":"John","last_name":"Doe","type":"NO_SEATBELT","fine_amount":22.157054761072807},{"date_time":"2008-02-11T00:00:00","first_name":"John","last_name":"Doe","type":"DRUNK_DRIVING","fine_amount":28.608953105754495},{"date_time":"2008-02-12T00:00:00","first_name":"John","last_name":"Doe","type":"NO_INSURANCE","fine_amount":68.0254393167365},{"date_time":"2008-02-13T00:00:00","first_name":"John","last_name":"Doe","type":"NO_SEATBELT","fine_amount":88.05220649399301},{"date_time":"2008-02-14T00:00:00","first_name":"John","last_name":"Doe","type":"RED_SIGNAL","fine_amount":40.84834367013946},{"date_time":"2008-02-15T00:00:00","first_name":"John","last_name":"Doe","type":"SPEEDING","fine_amount":16.603509660044004},{"date_time":"2008-02-16T00:00:00","first_name":"John","last_name":"Doe","type":"NO_SEATBELT","fine_amount":4.329113002934581},{"date_time":"2008-02-17T00:00:00","first_name":"John","last_name":"Doe","type":"NO_INSURANCE","fine_amount":89.13771763000443},{"date_time":"2008-02-18T00:00:00","first_name":"John","last_name":"Doe","type":"NO_SEATBELT","fine_amount":88.2263438563795},{"date_time":"2008-02-19T00:00:00","first_name":"John","last_name":"Doe","type":"SPEEDING","fine_amount":92.973973887614},{"date_time":"2008-02-20T00:00:00","first_name":"John","last_name":"Doe","type":"NO_SEATBELT","fine_amount":82.17852438157979},{"date_time":"2008-02-21T00:00:00","first_name":"John","last_name":"Doe","type":"DRUNK_DRIVING","fine_amount":19.307044640338624},{"date_time":"2008-02-22T00:00:00","first_name":"John","last_name":"Doe","type":"SPEEDING","fine_amount":20.170003754875424},{"date_time":"2008-02-23T00:00:00","first_name":"John","last_name":"Doe","type":"SPEEDING","fine_amount":72.28430411712141},{"date_time":"2008-02-24T00:00:00","first_name":"John","last_name":"Doe","type":"RED_SIGNAL","fine_amount":88.43088022909136},{"date_time":"2008-02-25T00:00:00","first_name":"John","last_name":"Doe","type":"RED_SIGNAL","fine_amount":57.54144863550601},{"date_time":"2008-02-26T00:00:00","first_name":"John","last_name":"Doe","type":"DRUNK_DRIVING","fine_amount":1.150834550804758},{"date_time":"2008-02-27T00:00:00","first_name":"John","last_name":"Doe","type":"NO_SEATBELT","fine_amount":40.38646387532774},{"date_time":"2008-02-28T00:00:00","first_name":"John","last_name":"Doe","type":"SPEEDING","fine_amount":9.533516268873624},{"date_time":"2008-02-29T00:00:00","first_name":"John","last_name":"Doe","type":"RED_SIGNAL","fine_amount":68.63933754292941},{"date_time":"2008-03-01T00:00:00","first_name":"John","last_name":"Doe","type":"DRUNK_DRIVING","fine_amount":67.70043652865965},{"date_time":"2008-03-02T00:00:00","first_name":"John","last_name":"Doe","type":"NO_SEATBELT","fine_amount":65.91316437359916},{"date_time":"2008-03-03T00:00:00","first_name":"John","last_name":"Doe","type":"SPEEDING","fine_amount":61.719446010447264},{"date_time":"2008-03-04T00:00:00","first_name":"John","last_name":"Doe","type":"SPEEDING","fine_amount":1.9260414382660307},{"date_time":"2008-03-05T00:00:00","first_name":"John","last_name":"Doe","type":"SPEEDING","fine_amount":91.95299816968185},{"date_time":"2008-03-06T00:00:00","first_name":"John","last_name":"Doe","type":"DRUNK_DRIVING","fine_amount":79.62474333109388},{"date_time":"2008-03-07T00:00:00","first_name":"John","last_name":"Doe","type":"NO_INSURANCE","fine_amount":77.53759809973802},{"date_time":"2008-03-08T00:00:00","first_name":"John","last_name":"Doe","type":"NO_SEATBELT","fine_amount":96.88976586167999},{"date_time":"2008-03-09T00:00:00","first_name":"John","last_name":"Doe","type":"NO_SEATBELT","fine_amount":3.5817390041600325},{"date_time":"2008-03-10T00:00:00","first_name":"John","last_name":"Doe","type":"NO_SEATBELT","fine_amount":26.58321633178881},{"date_time":"2008-03-11T00:00:00","first_name":"John","last_name":"Doe","type":"NO_INSURANCE","fine_amount":9.741261204110101},{"date_time":"2008-03-12T00:00:00","first_name":"John","last_name":"Doe","type":"NO_SEATBELT","fine_amount":37.44872415816087},{"date_time":"2008-03-13T00:00:00","first_name":"John","last_name":"Doe","type":"NO_INSURANCE","fine_amount":11.7558387113256},{"date_time":"2008-03-14T00:00:00","first_name":"John","last_name":"Doe","type":"SPEEDING","fine_amount":72.92627175346699},{"date_time":"2008-03-15T00:00:00","first_name":"John","last_name":"Doe","type":"NO_INSURANCE","fine_amount":18.037759590454776},{"date_time":"2008-03-16T00:00:00","first_name":"John","last_name":"Doe","type":"SPEEDING","fine_amount":82.40103346773732},{"date_time":"2008-03-17T00:00:00","first_name":"John","last_name":"Doe","type":"SPEEDING","fine_amount":59.145776053577904},{"date_time":"2008-03-18T00:00:00","first_name":"John","last_name":"Doe","type":"SPEEDING","fine_amount":56.65754872790551},{"date_time":"2008-03-19T00:00:00","first_name":"John","last_name":"Doe","type":"SPEEDING","fine_amount":14.275618848488822},{"date_time":"2008-03-20T00:00:00","first_name":"John","last_name":"Doe","type":"NO_SEATBELT","fine_amount":74.7993739455134},{"date_time":"2008-03-21T00:00:00","first_name":"John","last_name":"Doe","type":"NO_INSURANCE","fine_amount":5.500112272060088},{"date_time":"2008-03-22T00:00:00","first_name":"John","last_name":"Doe","type":"SPEEDING","fine_amount":74.35689976196375},{"date_time":"2008-03-23T00:00:00","first_name":"John","last_name":"Doe","type":"RED_SIGNAL","fine_amount":4.312499821687936},{"date_time":"2008-03-24T00:00:00","first_name":"John","last_name":"Doe","type":"DRUNK_DRIVING","fine_amount":35.526691042803336},{"date_time":"2008-03-25T00:00:00","first_name":"John","last_name":"Doe","type":"RED_SIGNAL","fine_amount":49.90565651622257},{"date_time":"2008-03-26T00:00:00","first_name":"John","last_name":"Doe","type":"RED_SIGNAL","fine_amount":94.04528608855287},{"date_time":"2008-03-27T00:00:00","first_name":"John","last_name":"Doe","type":"DRUNK_DRIVING","fine_amount":21.06785729213785},{"date_time":"2008-03-28T00:00:00","first_name":"John","last_name":"Doe","type":"RED_SIGNAL","fine_amount":66.22701807852702},{"date_time":"2008-03-29T00:00:00","first_name":"John","last_name":"Doe","type":"NO_SEATBELT","fine_amount":4.52548493252169},{"date_time":"2008-03-30T00:00:00","first_name":"John","last_name":"Doe","type":"SPEEDING","fine_amount":34.613882832605924},{"date_time":"2008-03-31T00:00:00","first_name":"John","last_name":"Doe","type":"NO_INSURANCE","fine_amount":11.118860258282037},{"date_time":"2008-04-01T00:00:00","first_name":"John","last_name":"Doe","type":"DRUNK_DRIVING","fine_amount":95.96728736888576},{"date_time":"2008-04-02T00:00:00","first_name":"John","last_name":"Doe","type":"NO_INSURANCE","fine_amount":89.38576884323602},{"date_time":"2008-04-03T00:00:00","first_name":"John","last_name":"Doe","type":"NO_SEATBELT","fine_amount":83.24542092788336},{"date_time":"2008-04-04T00:00:00","first_name":"John","last_name":"Doe","type":"SPEEDING","fine_amount":73.6462652483602},{"date_time":"2008-04-05T00:00:00","first_name":"John","last_name":"Doe","type":"SPEEDING","fine_amount":21.57137275340707},{"date_time":"2008-04-06T00:00:00","first_name":"John","last_name":"Doe","type":"SPEEDING","fine_amount":77.6523658171319},{"date_time":"2008-04-07T00:00:00","first_name":"John","last_name":"Doe","type":"SPEEDING","fine_amount":74.11814991205893},{"date_time":"2008-04-08T00:00:00","first_name":"John","last_name":"Doe","type":"NO_SEATBELT","fine_amount":54.57899347541584},{"date_time":"2008-04-09T00:00:00","first_name":"John","last_name":"Doe","type":"RED_SIGNAL","fine_amount":92.47679754069196},{"date_time":"2008-04-10T00:00:00","first_name":"John","last_name":"Doe","type":"DRUNK_DRIVING","fine_amount":59.80209473557729},{"date_time":"2008-04-11T00:00:00","first_name":"John","last_name":"Doe","type":"NO_INSURANCE","fine_amount":88.38887700687752},{"date_time":"2008-04-12T00:00:00","first_name":"John","last_name":"Doe","type":"SPEEDING","fine_amount":16.421874500346952},{"date_time":"2008-04-13T00:00:00","first_name":"John","last_name":"Doe","type":"DRUNK_DRIVING","fine_amount":76.21744053171157},{"date_time":"2008-04-14T00:00:00","first_name":"John","last_name":"Doe","type":"SPEEDING","fine_amount":63.151146506578506},{"date_time":"2008-04-15T00:00:00","first_name":"John","last_name":"Doe","type":"RED_SIGNAL","fine_amount":78.00127605037999},{"date_time":"2008-04-16T00:00:00","first_name":"John","last_name":"Doe","type":"NO_INSURANCE","fine_amount":31.48049259348754},{"date_time":"2008-04-17T00:00:00","first_name":"John","last_name":"Doe","type":"NO_INSURANCE","fine_amount":47.2323544128617},{"date_time":"2008-04-18T00:00:00","first_name":"John","last_name":"Doe","type":"NO_INSURANCE","fine_amount":30.35452992668435},{"date_time":"2008-04-19T00:00:00","first_name":"John","last_name":"Doe","type":"RED_SIGNAL","fine_amount":5.2592817458495515},{"date_time":"2008-04-20T00:00:00","first_name":"John","last_name":"Doe","type":"NO_INSURANCE","fine_amount":72.0203765077432},{"date_time":"2008-04-21T00:00:00","first_name":"John","last_name":"Doe","type":"SPEEDING","fine_amount":26.641081562800167},{"date_time":"2008-04-22T00:00:00","first_name":"John","last_name":"Doe","type":"RED_SIGNAL","fine_amount":89.73551639291924},{"date_time":"2008-04-23T00:00:00","first_name":"John","last_name":"Doe","type":"DRUNK_DRIVING","fine_amount":64.34265429285682},{"date_time":"2008-04-24T00:00:00","first_name":"John","last_name":"Doe","type":"DRUNK_DRIVING","fine_amount":80.31468613990145},{"date_time":"2008-04-25T00:00:00","first_name":"John","last_name":"Doe","type":"NO_INSURANCE","fine_amount":62.91019784670228},{"date_time":"2008-04-26T00:00:00","first_name":"John","last_name":"Doe","type":"RED_SIGNAL","fine_amount":76.64291212573616},{"date_time":"2008-04-27T00:00:00","first_name":"John","last_name":"Doe","type":"RED_SIGNAL","fine_amount":39.02287609278123},{"date_time":"2008-04-28T00:00:00","first_name":"John","last_name":"Doe","type":"RED_SIGNAL","fine_amount":59.54536412917483},{"date_time":"2008-04-29T00:00:00","first_name":"John","last_name":"Doe","type":"NO_SEATBELT","fine_amount":50.963596510894895},{"date_time":"2008-04-30T00:00:00","first_name":"John","last_name":"Doe","type":"RED_SIGNAL","fine_amount":56.46664637856701},{"date_time":"2008-05-01T00:00:00","first_name":"John","last_name":"Doe","type":"NO_SEATBELT","fine_amount":29.76230048119339},{"date_time":"2008-05-02T00:00:00","first_name":"John","last_name":"Doe","type":"DRUNK_DRIVING","fine_amount":35.12714768117912},{"date_time":"2008-05-03T00:00:00","first_name":"John","last_name":"Doe","type":"NO_SEATBELT","fine_amount":35.26083487628528},{"date_time":"2008-05-04T00:00:00","first_name":"John","last_name":"Doe","type":"NO_INSURANCE","fine_amount":58.46849338661512},{"date_time":"2008-05-05T00:00:00","first_name":"John","last_name":"Doe","type":"SPEEDING","fine_amount":70.14810116001262},{"date_time":"2008-05-06T00:00:00","first_name":"John","last_name":"Doe","type":"RED_SIGNAL","fine_amount":94.2221383996639},{"date_time":"2008-05-07T00:00:00","first_name":"John","last_name":"Doe","type":"NO_SEATBELT","fine_amount":99.68320163707035},{"date_time":"2008-05-08T00:00:00","first_name":"John","last_name":"Doe","type":"NO_SEATBELT","fine_amount":27.204877316434516},{"date_time":"2008-05-09T00:00:00","first_name":"John","last_name":"Doe","type":"NO_INSURANCE","fine_amount":80.22479874385108},{"date_time":"2008-05-10T00:00:00","first_name":"John","last_name":"Doe","type":"NO_INSURANCE","fine_amount":33.00458880079841},{"date_time":"2008-05-11T00:00:00","first_name":"John","last_name":"Doe","type":"DRUNK_DRIVING","fine_amount":54.726371827839294},{"date_time":"2008-05-12T00:00:00","first_name":"John","last_name":"Doe","type":"DRUNK_DRIVING","fine_amount":37.032567982604526},{"date_time":"2008-05-13T00:00:00","first_name":"John","last_name":"Doe","type":"DRUNK_DRIVING","fine_amount":15.745259689984877},{"date_time":"2008-05-14T00:00:00","first_name":"John","last_name":"Doe","type":"DRUNK_DRIVING","fine_amount":89.62127936464456},{"date_time":"2008-05-15T00:00:00","first_name":"John","last_name":"Doe","type":"NO_SEATBELT","fine_amount":20.501465682808487},{"date_time":"2008-05-16T00:00:00","first_name":"John","last_name":"Doe","type":"NO_SEATBELT","fine_amount":54.99571075574935},{"date_time":"2008-05-17T00:00:00","first_name":"John","last_name":"Doe","type":"RED_SIGNAL","fine_amount":95.65981616254966},{"date_time":"2008-05-18T00:00:00","first_name":"John","last_name":"Doe","type":"RED_SIGNAL","fine_amount":4.772422384164907},{"date_time":"2008-05-19T00:00:00","first_name":"John","last_name":"Doe","type":"SPEEDING","fine_amount":9.392997497756356},{"date_time":"2008-05-20T00:00:00","first_name":"John","last_name":"Doe","type":"RED_SIGNAL","fine_amount":57.29397461173453},{"date_time":"2008-05-21T00:00:00","first_name":"John","last_name":"Doe","type":"NO_SEATBELT","fine_amount":51.30675847022686},{"date_time":"2008-05-22T00:00:00","first_name":"John","last_name":"Doe","type":"NO_INSURANCE","fine_amount":61.41121132060975},{"date_time":"2008-05-23T00:00:00","first_name":"John","last_name":"Doe","type":"RED_SIGNAL","fine_amount":30.912585317397888},{"date_time":"2008-05-24T00:00:00","first_name":"John","last_name":"Doe","type":"SPEEDING","fine_amount":55.526753880574866},{"date_time":"2008-05-25T00:00:00","first_name":"John","last_name":"Doe","type":"NO_SEATBELT","fine_amount":82.75469365712848},{"date_time":"2008-05-26T00:00:00","first_name":"John","last_name":"Doe","type":"RED_SIGNAL","fine_amount":60.22714192028732},{"date_time":"2008-05-27T00:00:00","first_name":"John","last_name":"Doe","type":"NO_INSURANCE","fine_amount":94.32157178467864},{"date_time":"2008-05-28T00:00:00","first_name":"John","last_name":"Doe","type":"SPEEDING","fine_amount":25.997184750418516},{"date_time":"2008-05-29T00:00:00","first_name":"John","last_name":"Doe","type":"RED_SIGNAL","fine_amount":77.5784013062066},{"date_time":"2008-05-30T00:00:00","first_name":"John","last_name":"Doe","type":"RED_SIGNAL","fine_amount":88.33898728036274},{"date_time":"2008-05-31T00:00:00","first_name":"John","last_name":"Doe","type":"NO_SEATBELT","fine_amount":87.97352085132717},{"date_time":"2008-06-01T00:00:00","first_name":"John","last_name":"Doe","type":"NO_SEATBELT","fine_amount":76.54239038928597},{"date_time":"2008-06-02T00:00:00","first_name":"John","last_name":"Doe","type":"NO_SEATBELT","fine_amount":19.02454526380979},{"date_time":"2008-06-03T00:00:00","first_name":"John","last_name":"Doe","type":"SPEEDING","fine_amount":41.977791242233984},{"date_time":"2008-06-04T00:00:00","first_name":"John","last_name":"Doe","type":"NO_SEATBELT","fine_amount":96.04930846988047},{"date_time":"2008-06-05T00:00:00","first_name":"John","last_name":"Doe","type":"NO_SEATBELT","fine_amount":44.632718846125286},{"date_time":"2008-06-06T00:00:00","first_name":"John","last_name":"Doe","type":"RED_SIGNAL","fine_amount":20.042187777323143},{"date_time":"2008-06-07T00:00:00","first_name":"John","last_name":"Doe","type":"NO_INSURANCE","fine_amount":97.88848539492214},{"date_time":"2008-06-08T00:00:00","first_name":"John","last_name":"Doe","type":"DRUNK_DRIVING","fine_amount":95.42295675324188},{"date_time":"2008-06-09T00:00:00","first_name":"John","last_name":"Doe","type":"NO_INSURANCE","fine_amount":47.852855018296566},{"date_time":"2008-06-10T00:00:00","first_name":"John","last_name":"Doe","type":"DRUNK_DRIVING","fine_amount":95.01537506188735},{"date_time":"2008-06-11T00:00:00","first_name":"John","last_name":"Doe","type":"DRUNK_DRIVING","fine_amount":11.720719835643537},{"date_time":"2008-06-12T00:00:00","first_name":"John","last_name":"Doe","type":"RED_SIGNAL","fine_amount":97.8054836755806},{"date_time":"2008-06-13T00:00:00","first_name":"John","last_name":"Doe","type":"NO_INSURANCE","fine_amount":96.34156749917754},{"date_time":"2008-06-14T00:00:00","first_name":"John","last_name":"Doe","type":"SPEEDING","fine_amount":98.24108369662228},{"date_time":"2008-06-15T00:00:00","first_name":"John","last_name":"Doe","type":"SPEEDING","fine_amount":64.81526796631616},{"date_time":"2008-06-16T00:00:00","first_name":"John","last_name":"Doe","type":"NO_SEATBELT","fine_amount":42.06703269904445},{"date_time":"2008-06-17T00:00:00","first_name":"John","last_name":"Doe","type":"DRUNK_DRIVING","fine_amount":2.324454691596822},{"date_time":"2008-06-18T00:00:00","first_name":"John","last_name":"Doe","type":"RED_SIGNAL","fine_amount":9.24563728541466},{"date_time":"2008-06-19T00:00:00","first_name":"John","last_name":"Doe","type":"DRUNK_DRIVING","fine_amount":91.52183249030094},{"date_time":"2008-06-20T00:00:00","first_name":"John","last_name":"Doe","type":"NO_INSURANCE","fine_amount":28.73419188773615},{"date_time":"2008-06-21T00:00:00","first_name":"John","last_name":"Doe","type":"DRUNK_DRIVING","fine_amount":89.52540284326308},{"date_time":"2008-06-22T00:00:00","first_name":"John","last_name":"Doe","type":"NO_SEATBELT","fine_amount":28.926259067923272},{"date_time":"2008-06-23T00:00:00","first_name":"John","last_name":"Doe","type":"NO_INSURANCE","fine_amount":47.507303896997115},{"date_time":"2008-06-24T00:00:00","first_name":"John","last_name":"Doe","type":"RED_SIGNAL","fine_amount":81.09984140782804},{"date_time":"2008-06-25T00:00:00","first_name":"John","last_name":"Doe","type":"DRUNK_DRIVING","fine_amount":99.98765899345257},{"date_time":"2008-06-26T00:00:00","first_name":"John","last_name":"Doe","type":"DRUNK_DRIVING","fine_amount":54.24174223644856},{"date_time":"2008-06-27T00:00:00","first_name":"John","last_name":"Doe","type":"SPEEDING","fine_amount":87.4305881702578},{"date_time":"2008-06-28T00:00:00","first_name":"John","last_name":"Doe","type":"DRUNK_DRIVING","fine_amount":59.167072959270676},{"date_time":"2008-06-29T00:00:00","first_name":"John","last_name":"Doe","type":"SPEEDING","fine_amount":97.6742034294036},{"date_time":"2008-06-30T00:00:00","first_name":"John","last_name":"Doe","type":"DRUNK_DRIVING","fine_amount":12.757227743818525},{"date_time":"2008-07-01T00:00:00","first_name":"John","last_name":"Doe","type":"NO_INSURANCE","fine_amount":6.870767592130635},{"date_time":"2008-07-02T00:00:00","first_name":"John","last_name":"Doe","type":"DRUNK_DRIVING","fine_amount":89.77663087954167},{"date_time":"2008-07-03T00:00:00","first_name":"John","last_name":"Doe","type":"NO_INSURANCE","fine_amount":10.149752050909177},{"date_time":"2008-07-04T00:00:00","first_name":"John","last_name":"Doe","type":"RED_SIGNAL","fine_amount":24.772960827899535},{"date_time":"2008-07-05T00:00:00","first_name":"John","last_name":"Doe","type":"DRUNK_DRIVING","fine_amount":40.499923685171794},{"date_time":"2008-07-06T00:00:00","first_name":"John","last_name":"Doe","type":"NO_INSURANCE","fine_amount":7.738997312736861},{"date_time":"2008-07-07T00:00:00","first_name":"John","last_name":"Doe","type":"NO_INSURANCE","fine_amount":65.6731228170234},{"date_time":"2008-07-08T00:00:00","first_name":"John","last_name":"Doe","type":"RED_SIGNAL","fine_amount":43.03537498933566},{"date_time":"2008-07-09T00:00:00","first_name":"John","last_name":"Doe","type":"SPEEDING","fine_amount":70.1901601545465},{"date_time":"2008-07-10T00:00:00","first_name":"John","last_name":"Doe","type":"NO_INSURANCE","fine_amount":55.607718353189725},{"date_time":"2008-07-11T00:00:00","first_name":"John","last_name":"Doe","type":"SPEEDING","fine_amount":3.1487795875645563},{"date_time":"2008-07-12T00:00:00","first_name":"John","last_name":"Doe","type":"NO_SEATBELT","fine_amount":23.14120160585268},{"date_time":"2008-07-13T00:00:00","first_name":"John","last_name":"Doe","type":"DRUNK_DRIVING","fine_amount":4.03635039987642},{"date_time":"2008-07-14T00:00:00","first_name":"John","last_name":"Doe","type":"DRUNK_DRIVING","fine_amount":9.889683653281844},{"date_time":"2008-07-15T00:00:00","first_name":"John","last_name":"Doe","type":"RED_SIGNAL","fine_amount":59.600218538395616},{"date_time":"2008-07-16T00:00:00","first_name":"John","last_name":"Doe","type":"NO_INSURANCE","fine_amount":39.70135214878068},{"date_time":"2008-07-17T00:00:00","first_name":"John","last_name":"Doe","type":"SPEEDING","fine_amount":46.161928270624244},{"date_time":"2008-07-18T00:00:00","first_name":"John","last_name":"Doe","type":"NO_SEATBELT","fine_amount":85.99105138764044},{"date_time":"2008-07-19T00:00:00","first_name":"John","last_name":"Doe","type":"DRUNK_DRIVING","fine_amount":89.13553560538443},{"date_time":"2008-07-20T00:00:00","first_name":"John","last_name":"Doe","type":"RED_SIGNAL","fine_amount":34.131115292232906},{"date_time":"2008-07-21T00:00:00","first_name":"John","last_name":"Doe","type":"RED_SIGNAL","fine_amount":43.65442685633306},{"date_time":"2008-07-22T00:00:00","first_name":"John","last_name":"Doe","type":"RED_SIGNAL","fine_amount":69.04419289207436},{"date_time":"2008-07-23T00:00:00","first_name":"John","last_name":"Doe","type":"RED_SIGNAL","fine_amount":82.77683402212722},{"date_time":"2008-07-24T00:00:00","first_name":"John","last_name":"Doe","type":"NO_SEATBELT","fine_amount":69.5767752008503},{"date_time":"2008-07-25T00:00:00","first_name":"John","last_name":"Doe","type":"RED_SIGNAL","fine_amount":91.05085391837746},{"date_time":"2008-07-26T00:00:00","first_name":"John","last_name":"Doe","type":"SPEEDING","fine_amount":50.951394617155195},{"date_time":"2008-07-27T00:00:00","first_name":"John","last_name":"Doe","type":"DRUNK_DRIVING","fine_amount":1.0202553337439761},{"date_time":"2008-07-28T00:00:00","first_name":"John","last_name":"Doe","type":"DRUNK_DRIVING","fine_amount":17.976033890015295},{"date_time":"2008-07-29T00:00:00","first_name":"John","last_name":"Doe","type":"SPEEDING","fine_amount":95.45984300564928},{"date_time":"2008-07-30T00:00:00","first_name":"John","last_name":"Doe","type":"NO_INSURANCE","fine_amount":96.51532201076343},{"date_time":"2008-07-31T00:00:00","first_name":"John","last_name":"Doe","type":"RED_SIGNAL","fine_amount":89.58231283859554},{"date_time":"2008-08-01T00:00:00","first_name":"John","last_name":"Doe","type":"NO_INSURANCE","fine_amount":37.58073959186867},{"date_time":"2008-08-02T00:00:00","first_name":"John","last_name":"Doe","type":"NO_SEATBELT","fine_amount":94.66837923189735},{"date_time":"2008-08-03T00:00:00","first_name":"John","last_name":"Doe","type":"DRUNK_DRIVING","fine_amount":81.40412700341412},{"date_time":"2008-08-04T00:00:00","first_name":"John","last_name":"Doe","type":"DRUNK_DRIVING","fine_amount":71.47077439222613},{"date_time":"2008-08-05T00:00:00","first_name":"John","last_name":"Doe","type":"DRUNK_DRIVING","fine_amount":17.445151447367664},{"date_time":"2008-08-06T00:00:00","first_name":"John","last_name":"Doe","type":"DRUNK_DRIVING","fine_amount":35.435310810632814},{"date_time":"2008-08-07T00:00:00","first_name":"John","last_name":"Doe","type":"NO_SEATBELT","fine_amount":90.92077592006129},{"date_time":"2008-08-08T00:00:00","first_name":"John","last_name":"Doe","type":"SPEEDING","fine_amount":61.2947707307174},{"date_time":"2008-08-09T00:00:00","first_name":"John","last_name":"Doe","type":"DRUNK_DRIVING","fine_amount":40.40157264247973},{"date_time":"2008-08-10T00:00:00","first_name":"John","last_name":"Doe","type":"RED_SIGNAL","fine_amount":32.62212858930734},{"date_time":"2008-08-11T00:00:00","first_name":"John","last_name":"Doe","type":"SPEEDING","fine_amount":2.111589042953454},{"date_time":"2008-08-12T00:00:00","first_name":"John","last_name":"Doe","type":"RED_SIGNAL","fine_amount":9.598853998697118},{"date_time":"2008-08-13T00:00:00","first_name":"John","last_name":"Doe","type":"NO_INSURANCE","fine_amount":96.90748228961806},{"date_time":"2008-08-14T00:00:00","first_name":"John","last_name":"Doe","type":"NO_SEATBELT","fine_amount":40.85350945589276},{"date_time":"2008-08-15T00:00:00","first_name":"John","last_name":"Doe","type":"NO_SEATBELT","fine_amount":33.658191937937},{"date_time":"2008-08-16T00:00:00","first_name":"John","last_name":"Doe","type":"NO_SEATBELT","fine_amount":32.969660113524434},{"date_time":"2008-08-17T00:00:00","first_name":"John","last_name":"Doe","type":"NO_INSURANCE","fine_amount":24.854333704827674},{"date_time":"2008-08-18T00:00:00","first_name":"John","last_name":"Doe","type":"RED_SIGNAL","fine_amount":91.0358136490066},{"date_time":"2008-08-19T00:00:00","first_name":"John","last_name":"Doe","type":"DRUNK_DRIVING","fine_amount":60.24997876633222},{"date_time":"2008-08-20T00:00:00","first_name":"John","last_name":"Doe","type":"NO_SEATBELT","fine_amount":32.7214048777128},{"date_time":"2008-08-21T00:00:00","first_name":"John","last_name":"Doe","type":"DRUNK_DRIVING","fine_amount":54.97801487954662},{"date_time":"2008-08-22T00:00:00","first_name":"John","last_name":"Doe","type":"SPEEDING","fine_amount":62.29126886184488},{"date_time":"2008-08-23T00:00:00","first_name":"John","last_name":"Doe","type":"DRUNK_DRIVING","fine_amount":91.73089567812069},{"date_time":"2008-08-24T00:00:00","first_name":"John","last_name":"Doe","type":"SPEEDING","fine_amount":84.11782668966369},{"date_time":"2008-08-25T00:00:00","first_name":"John","last_name":"Doe","type":"NO_SEATBELT","fine_amount":90.90450180574406},{"date_time":"2008-08-26T00:00:00","first_name":"John","last_name":"Doe","type":"RED_SIGNAL","fine_amount":87.68876643638177},{"date_time":"2008-08-27T00:00:00","first_name":"John","last_name":"Doe","type":"RED_SIGNAL","fine_amount":88.25474262641112},{"date_time":"2008-08-28T00:00:00","first_name":"John","last_name":"Doe","type":"NO_SEATBELT","fine_amount":22.333308963168992},{"date_time":"2008-08-29T00:00:00","first_name":"John","last_name":"Doe","type":"NO_SEATBELT","fine_amount":65.10155507126794},{"date_time":"2008-08-30T00:00:00","first_name":"John","last_name":"Doe","type":"SPEEDING","fine_amount":21.56924637809997},{"date_time":"2008-08-31T00:00:00","first_name":"John","last_name":"Doe","type":"NO_SEATBELT","fine_amount":60.96742093077842},{"date_time":"2008-09-01T00:00:00","first_name":"John","last_name":"Doe","type":"NO_INSURANCE","fine_amount":33.69477884975546},{"date_time":"2008-09-02T00:00:00","first_name":"John","last_name":"Doe","type":"NO_INSURANCE","fine_amount":32.08834103757184},{"date_time":"2008-09-03T00:00:00","first_name":"John","last_name":"Doe","type":"RED_SIGNAL","fine_amount":15.27430907159663},{"date_time":"2008-09-04T00:00:00","first_name":"John","last_name":"Doe","type":"DRUNK_DRIVING","fine_amount":6.362440196659138},{"date_time":"2008-09-05T00:00:00","first_name":"John","last_name":"Doe","type":"RED_SIGNAL","fine_amount":21.17857818871652},{"date_time":"2008-09-06T00:00:00","first_name":"John","last_name":"Doe","type":"NO_INSURANCE","fine_amount":57.179717486614834},{"date_time":"2008-09-07T00:00:00","first_name":"John","last_name":"Doe","type":"NO_SEATBELT","fine_amount":98.69128699105966},{"date_time":"2008-09-08T00:00:00","first_name":"John","last_name":"Doe","type":"DRUNK_DRIVING","fine_amount":76.42771141925427},{"date_time":"2008-09-09T00:00:00","first_name":"John","last_name":"Doe","type":"NO_SEATBELT","fine_amount":89.6629115483533},{"date_time":"2008-09-10T00:00:00","first_name":"John","last_name":"Doe","type":"NO_SEATBELT","fine_amount":96.8103900706123},{"date_time":"2008-09-11T00:00:00","first_name":"John","last_name":"Doe","type":"DRUNK_DRIVING","fine_amount":92.22615877136835},{"date_time":"2008-09-12T00:00:00","first_name":"John","last_name":"Doe","type":"DRUNK_DRIVING","fine_amount":41.017050167487724},{"date_time":"2008-09-13T00:00:00","first_name":"John","last_name":"Doe","type":"SPEEDING","fine_amount":67.05654872224683},{"date_time":"2008-09-14T00:00:00","first_name":"John","last_name":"Doe","type":"DRUNK_DRIVING","fine_amount":34.096547715177486},{"date_time":"2008-09-15T00:00:00","first_name":"John","last_name":"Doe","type":"SPEEDING","fine_amount":99.60770790665617},{"date_time":"2008-09-16T00:00:00","first_name":"John","last_name":"Doe","type":"DRUNK_DRIVING","fine_amount":87.53902300019735},{"date_time":"2008-09-17T00:00:00","first_name":"John","last_name":"Doe","type":"RED_SIGNAL","fine_amount":65.13836475602692},{"date_time":"2008-09-18T00:00:00","first_name":"John","last_name":"Doe","type":"SPEEDING","fine_amount":28.748565311217725},{"date_time":"2008-09-19T00:00:00","first_name":"John","last_name":"Doe","type":"SPEEDING","fine_amount":18.312136461545265},{"date_time":"2008-09-20T00:00:00","first_name":"John","last_name":"Doe","type":"NO_INSURANCE","fine_amount":50.058688447845675},{"date_time":"2008-09-21T00:00:00","first_name":"John","last_name":"Doe","type":"RED_SIGNAL","fine_amount":56.74985952686603},{"date_time":"2008-09-22T00:00:00","first_name":"John","last_name":"Doe","type":"RED_SIGNAL","fine_amount":76.74821415150686},{"date_time":"2008-09-23T00:00:00","first_name":"John","last_name":"Doe","type":"DRUNK_DRIVING","fine_amount":89.37670005588319},{"date_time":"2008-09-24T00:00:00","first_name":"John","last_name":"Doe","type":"RED_SIGNAL","fine_amount":75.25444935422281},{"date_time":"2008-09-25T00:00:00","first_name":"John","last_name":"Doe","type":"NO_INSURANCE","fine_amount":44.88427219285524},{"date_time":"2008-09-26T00:00:00","first_name":"John","last_name":"Doe","type":"RED_SIGNAL","fine_amount":3.347338094057786},{"date_time":"2008-09-27T00:00:00","first_name":"John","last_name":"Doe","type":"NO_SEATBELT","fine_amount":27.944337064983642},{"date_time":"2008-09-28T00:00:00","first_name":"John","last_name":"Doe","type":"DRUNK_DRIVING","fine_amount":43.362699221607436},{"date_time":"2008-09-29T00:00:00","first_name":"John","last_name":"Doe","type":"NO_SEATBELT","fine_amount":61.21088483797163},{"date_time":"2008-09-30T00:00:00","first_name":"John","last_name":"Doe","type":"SPEEDING","fine_amount":3.932285362973046},{"date_time":"2008-10-01T00:00:00","first_name":"John","last_name":"Doe","type":"DRUNK_DRIVING","fine_amount":45.0480940225214},{"date_time":"2008-10-02T00:00:00","first_name":"John","last_name":"Doe","type":"DRUNK_DRIVING","fine_amount":43.27707424466741},{"date_time":"2008-10-03T00:00:00","first_name":"John","last_name":"Doe","type":"SPEEDING","fine_amount":64.6620988840371},{"date_time":"2008-10-04T00:00:00","first_name":"John","last_name":"Doe","type":"SPEEDING","fine_amount":73.12944666589084},{"date_time":"2008-10-05T00:00:00","first_name":"John","last_name":"Doe","type":"DRUNK_DRIVING","fine_amount":22.905032014361048},{"date_time":"2008-10-06T00:00:00","first_name":"John","last_name":"Doe","type":"RED_SIGNAL","fine_amount":52.347102305315005},{"date_time":"2008-10-07T00:00:00","first_name":"John","last_name":"Doe","type":"SPEEDING","fine_amount":52.89340263118624},{"date_time":"2008-10-08T00:00:00","first_name":"John","last_name":"Doe","type":"RED_SIGNAL","fine_amount":64.2020059855256},{"date_time":"2008-10-09T00:00:00","first_name":"John","last_name":"Doe","type":"NO_INSURANCE","fine_amount":69.3436910543882},{"date_time":"2008-10-10T00:00:00","first_name":"John","last_name":"Doe","type":"DRUNK_DRIVING","fine_amount":28.14269330699058},{"date_time":"2008-10-11T00:00:00","first_name":"John","last_name":"Doe","type":"DRUNK_DRIVING","fine_amount":53.702782674495445},{"date_time":"2008-10-12T00:00:00","first_name":"John","last_name":"Doe","type":"NO_INSURANCE","fine_amount":6.3066306408447685},{"date_time":"2008-10-13T00:00:00","first_name":"John","last_name":"Doe","type":"SPEEDING","fine_amount":20.93748639547031},{"date_time":"2008-10-14T00:00:00","first_name":"John","last_name":"Doe","type":"RED_SIGNAL","fine_amount":1.5163406918339866},{"date_time":"2008-10-15T00:00:00","first_name":"John","last_name":"Doe","type":"NO_SEATBELT","fine_amount":10.866163507510251},{"date_time":"2008-10-16T00:00:00","first_name":"John","last_name":"Doe","type":"SPEEDING","fine_amount":2.541087778453853},{"date_time":"2008-10-17T00:00:00","first_name":"John","last_name":"Doe","type":"SPEEDING","fine_amount":57.95838379168358},{"date_time":"2008-10-18T00:00:00","first_name":"John","last_name":"Doe","type":"NO_INSURANCE","fine_amount":1.7041018079144725},{"date_time":"2008-10-19T00:00:00","first_name":"John","last_name":"Doe","type":"DRUNK_DRIVING","fine_amount":28.309424712453925},{"date_time":"2008-10-20T00:00:00","first_name":"John","last_name":"Doe","type":"RED_SIGNAL","fine_amount":41.91983466999675},{"date_time":"2008-10-21T00:00:00","first_name":"John","last_name":"Doe","type":"SPEEDING","fine_amount":33.400935454370014},{"date_time":"2008-10-22T00:00:00","first_name":"John","last_name":"Doe","type":"NO_INSURANCE","fine_amount":61.95933449231618},{"date_time":"2008-10-23T00:00:00","first_name":"John","last_name":"Doe","type":"RED_SIGNAL","fine_amount":8.095097076391603},{"date_time":"2008-10-24T00:00:00","first_name":"John","last_name":"Doe","type":"NO_SEATBELT","fine_amount":7.464459077301098},{"date_time":"2008-10-25T00:00:00","first_name":"John","last_name":"Doe","type":"SPEEDING","fine_amount":15.056282863518147},{"date_time":"2008-10-26T00:00:00","first_name":"John","last_name":"Doe","type":"RED_SIGNAL","fine_amount":59.30988322317149},{"date_time":"2008-10-27T00:00:00","first_name":"John","last_name":"Doe","type":"RED_SIGNAL","fine_amount":54.35320789609514},{"date_time":"2008-10-28T00:00:00","first_name":"John","last_name":"Doe","type":"NO_INSURANCE","fine_amount":40.489366792433714},{"date_time":"2008-10-29T00:00:00","first_name":"John","last_name":"Doe","type":"RED_SIGNAL","fine_amount":83.93891836369268},{"date_time":"2008-10-30T00:00:00","first_name":"John","last_name":"Doe","type":"NO_SEATBELT","fine_amount":11.469768196056918},{"date_time":"2008-10-31T00:00:00","first_name":"John","last_name":"Doe","type":"NO_SEATBELT","fine_amount":9.030899187074738},{"date_time":"2008-11-01T00:00:00","first_name":"John","last_name":"Doe","type":"SPEEDING","fine_amount":39.90044280675949},{"date_time":"2008-11-02T00:00:00","first_name":"John","last_name":"Doe","type":"RED_SIGNAL","fine_amount":58.28606587251351},{"date_time":"2008-11-03T00:00:00","first_name":"John","last_name":"Doe","type":"NO_SEATBELT","fine_amount":24.72070171142001},{"date_time":"2008-11-04T00:00:00","first_name":"John","last_name":"Doe","type":"SPEEDING","fine_amount":16.174294931746637},{"date_time":"2008-11-05T00:00:00","first_name":"John","last_name":"Doe","type":"NO_INSURANCE","fine_amount":77.90546927469534},{"date_time":"2008-11-06T00:00:00","first_name":"John","last_name":"Doe","type":"DRUNK_DRIVING","fine_amount":15.860201442159218},{"date_time":"2008-11-07T00:00:00","first_name":"John","last_name":"Doe","type":"SPEEDING","fine_amount":11.706609346957311},{"date_time":"2008-11-08T00:00:00","first_name":"John","last_name":"Doe","type":"NO_INSURANCE","fine_amount":21.388671441861415},{"date_time":"2008-11-09T00:00:00","first_name":"John","last_name":"Doe","type":"RED_SIGNAL","fine_amount":9.959845385895845},{"date_time":"2008-11-10T00:00:00","first_name":"John","last_name":"Doe","type":"RED_SIGNAL","fine_amount":70.38978335874792},{"date_time":"2008-11-11T00:00:00","first_name":"John","last_name":"Doe","type":"RED_SIGNAL","fine_amount":3.556042922094287},{"date_time":"2008-11-12T00:00:00","first_name":"John","last_name":"Doe","type":"NO_SEATBELT","fine_amount":46.149422615685616},{"date_time":"2008-11-13T00:00:00","first_name":"John","last_name":"Doe","type":"DRUNK_DRIVING","fine_amount":11.039786668173786},{"date_time":"2008-11-14T00:00:00","first_name":"John","last_name":"Doe","type":"SPEEDING","fine_amount":47.68150716278802},{"date_time":"2008-11-15T00:00:00","first_name":"John","last_name":"Doe","type":"DRUNK_DRIVING","fine_amount":89.56282022373135},{"date_time":"2008-11-16T00:00:00","first_name":"John","last_name":"Doe","type":"NO_INSURANCE","fine_amount":82.75637035618732},{"date_time":"2008-11-17T00:00:00","first_name":"John","last_name":"Doe","type":"DRUNK_DRIVING","fine_amount":25.447406772133064},{"date_time":"2008-11-18T00:00:00","first_name":"John","last_name":"Doe","type":"DRUNK_DRIVING","fine_amount":68.2293168723202},{"date_time":"2008-11-19T00:00:00","first_name":"John","last_name":"Doe","type":"SPEEDING","fine_amount":75.81437154719755},{"date_time":"2008-11-20T00:00:00","first_name":"John","last_name":"Doe","type":"DRUNK_DRIVING","fine_amount":18.937875390512563},{"date_time":"2008-11-21T00:00:00","first_name":"John","last_name":"Doe","type":"SPEEDING","fine_amount":23.308179302474958},{"date_time":"2008-11-22T00:00:00","first_name":"John","last_name":"Doe","type":"NO_INSURANCE","fine_amount":91.03126712930501},{"date_time":"2008-11-23T00:00:00","first_name":"John","last_name":"Doe","type":"NO_SEATBELT","fine_amount":89.66022300458638},{"date_time":"2008-11-24T00:00:00","first_name":"John","last_name":"Doe","type":"DRUNK_DRIVING","fine_amount":82.41877669234388},{"date_time":"2008-11-25T00:00:00","first_name":"John","last_name":"Doe","type":"RED_SIGNAL","fine_amount":59.721099139590066},{"date_time":"2008-11-26T00:00:00","first_name":"John","last_name":"Doe","type":"DRUNK_DRIVING","fine_amount":8.804715632122903},{"date_time":"2008-11-27T00:00:00","first_name":"John","last_name":"Doe","type":"RED_SIGNAL","fine_amount":15.75971422665486},{"date_time":"2008-11-28T00:00:00","first_name":"John","last_name":"Doe","type":"DRUNK_DRIVING","fine_amount":4.167617484820806},{"date_time":"2008-11-29T00:00:00","first_name":"John","last_name":"Doe","type":"NO_SEATBELT","fine_amount":25.165357355417942},{"date_time":"2008-11-30T00:00:00","first_name":"John","last_name":"Doe","type":"SPEEDING","fine_amount":27.86361019299061},{"date_time":"2008-12-01T00:00:00","first_name":"John","last_name":"Doe","type":"DRUNK_DRIVING","fine_amount":8.63850286934877},{"date_time":"2008-12-02T00:00:00","first_name":"John","last_name":"Doe","type":"RED_SIGNAL","fine_amount":37.53367963511321},{"date_time":"2008-12-03T00:00:00","first_name":"John","last_name":"Doe","type":"DRUNK_DRIVING","fine_amount":94.2547237005974},{"date_time":"2008-12-04T00:00:00","first_name":"John","last_name":"Doe","type":"NO_SEATBELT","fine_amount":53.588654844583694},{"date_time":"2008-12-05T00:00:00","first_name":"John","last_name":"Doe","type":"NO_INSURANCE","fine_amount":51.217558768449756},{"date_time":"2008-12-06T00:00:00","first_name":"John","last_name":"Doe","type":"NO_INSURANCE","fine_amount":32.073234969990466},{"date_time":"2008-12-07T00:00:00","first_name":"John","last_name":"Doe","type":"NO_SEATBELT","fine_amount":66.26181543479912},{"date_time":"2008-12-08T00:00:00","first_name":"John","last_name":"Doe","type":"RED_SIGNAL","fine_amount":99.68181642879738},{"date_time":"2008-12-09T00:00:00","first_name":"John","last_name":"Doe","type":"NO_INSURANCE","fine_amount":52.6562881291464},{"date_time":"2008-12-10T00:00:00","first_name":"John","last_name":"Doe","type":"RED_SIGNAL","fine_amount":81.54703723106172},{"date_time":"2008-12-11T00:00:00","first_name":"John","last_name":"Doe","type":"SPEEDING","fine_amount":34.00929242838369},{"date_time":"2008-12-12T00:00:00","first_name":"John","last_name":"Doe","type":"NO_INSURANCE","fine_amount":60.25119126504992},{"date_time":"2008-12-13T00:00:00","first_name":"John","last_name":"Doe","type":"RED_SIGNAL","fine_amount":36.073127712862096},{"date_time":"2008-12-14T00:00:00","first_name":"John","last_name":"Doe","type":"NO_INSURANCE","fine_amount":26.347463354796187},{"date_time":"2008-12-15T00:00:00","first_name":"John","last_name":"Doe","type":"NO_INSURANCE","fine_amount":79.74352879805588},{"date_time":"2008-12-16T00:00:00","first_name":"John","last_name":"Doe","type":"NO_SEATBELT","fine_amount":91.22044593015154},{"date_time":"2008-12-17T00:00:00","first_name":"John","last_name":"Doe","type":"SPEEDING","fine_amount":81.27232945460136},{"date_time":"2008-12-18T00:00:00","first_name":"John","last_name":"Doe","type":"SPEEDING","fine_amount":41.483787844358545},{"date_time":"2008-12-19T00:00:00","first_name":"John","last_name":"Doe","type":"NO_SEATBELT","fine_amount":5.468653778647539},{"date_time":"2008-12-20T00:00:00","first_name":"John","last_name":"Doe","type":"DRUNK_DRIVING","fine_amount":65.5990671892576},{"date_time":"2008-12-21T00:00:00","first_name":"John","last_name":"Doe","type":"DRUNK_DRIVING","fine_amount":77.5149253157134},{"date_time":"2008-12-22T00:00:00","first_name":"John","last_name":"Doe","type":"SPEEDING","fine_amount":90.21798819442411},{"date_time":"2008-12-23T00:00:00","first_name":"John","last_name":"Doe","type":"RED_SIGNAL","fine_amount":75.92487565519875},{"date_time":"2008-12-24T00:00:00","first_name":"John","last_name":"Doe","type":"RED_SIGNAL","fine_amount":74.78537535409468},{"date_time":"2008-12-25T00:00:00","first_name":"John","last_name":"Doe","type":"RED_SIGNAL","fine_amount":6.624673773803158},{"date_time":"2008-12-26T00:00:00","first_name":"John","last_name":"Doe","type":"NO_INSURANCE","fine_amount":89.5010644619669},{"date_time":"2008-12-27T00:00:00","first_name":"John","last_name":"Doe","type":"SPEEDING","fine_amount":87.94483220303802},{"date_time":"2008-12-28T00:00:00","first_name":"John","last_name":"Doe","type":"NO_INSURANCE","fine_amount":83.30377607554124},{"date_time":"2008-12-29T00:00:00","first_name":"John","last_name":"Doe","type":"DRUNK_DRIVING","fine_amount":41.31656951066614},{"date_time":"2008-12-30T00:00:00","first_name":"John","last_name":"Doe","type":"DRUNK_DRIVING","fine_amount":69.5112390140261},{"date_time":"2008-12-31T00:00:00","first_name":"John","last_name":"Doe","type":"NO_SEATBELT","fine_amount":46.315254794829514}]